wedat/__init__.py
foyou_wedat-0.0.5.dist-info/LICENSE
foyou_wedat-0.0.5.dist-info/METADATA
foyou_wedat-0.0.5.dist-info/WHEEL
foyou_wedat-0.0.5.dist-info/entry_points.txt
foyou_wedat-0.0.5.dist-info/top_level.txt
foyou_wedat-0.0.5.dist-info/RECORD
